Workbook

Sheet 预算与测算
A1: 社区老年高血压患者家庭血压自测支持 RCT（12 个月）预算及测算依据
A2: 状态声明：本预算全部为规划假设（资料类型：虚构项目申报条件）。设备单价、人力成本、招募能力均【待确认】，设备询价与规模锁定后须重算。经费上限 10 万元。
A4: 一、输入假设（测算基准，均为规划假设）
A5: 总样本量（例，测算基准） | C5: 336 | D5: 对应样本量敏感性矩阵 δ=5/SD=15 或 δ=4/SD=12 组合；δ 与 SD 均为待确认参数，规模未锁定
A6: 干预组例数（例） | C6: =ROUND(C5/2,0) -> 168 | D6: 1:1 分组；由总样本量推导
A7: 对照组例数（例） | C7: =C5-C6 -> 168 | D7: 由总样本量与干预组推导
A8: 备机比例 | C8: 0.05 | D8: 备用设备管理方案；规划假设
A9: 血压计单价（元/台） | C9: 220 | D9: 经验证上臂式自动血压计；【待询价】
A10: 不可预见费率 | C10: 0.05 | D10: 规划假设
A11: 经费上限（元） | C11: 100000 | D11: 按基金申报要求，上限 10 万元（规划假设）
A13: 二、分项预算与测算依据
A14: 序号 | B14: 科目 | C14: 内容与用途 | D14: 联动类型 | E14: 折算系数 | F14: 数量 | G14: 单价（元） | H14: 金额（元） | I14: 测算依据与状态 | J14: 单位例数金额
A15: 1 | B15: 设备费 | C15: 干预组经验证上臂式自动血压计（含备机） | D15: 干预例数 | E15: =1+$C$8 -> 1.05 | F15: =ROUND($C$6*E15,0) -> 176 | G15: =$C$9 -> 220 | H15: =IF(OR(F15="",G15=""),"",F15*G15) -> 38720 | I15: 台数=干预例数×(1+备机比例 5%)；单价【待询价】；规划假设 | J15: =IF(D15="固定",H15,E15*G15) -> 231
A16: 2 | B16: 设备费 | C16: 两社区诊室血压计定期校准（2 台×2 次） | D16: 固定 | E16: 1 | F16: 4 | G16: 200 | H16: =IF(OR(F16="",G16=""),"",F16*G16) -> 800 | I16: 校准频次与费用【待确认】；规划假设 | J16: =IF(D16="固定",H16,E16*G16) -> 800
A17: 3 | B17: 材料费 | C17: 干预组备用袖带、电池等耗材 | D17: 干预例数 | E17: 1 | F17: =ROUND($C$6*E17,0) -> 168 | G17: 20 | H17: =IF(OR(F17="",G17=""),"",F17*G17) -> 3360 | I17: 每例约 20 元耗材；规划假设 | J17: =IF(D17="固定",H17,E17*G17) -> 20
A18: 4 | B18: 材料费 | C18: 家庭测量记录本与文具 | D18: 总例数 | E18: 1 | F18: =ROUND($C$5*E18,0) -> 336 | G18: 8 | H18: =IF(OR(F18="",G18=""),"",F18*G18) -> 2688 | I18: 每例 1 册记录本；规划假设 | J18: =IF(D18="固定",H18,E18*G18) -> 8
A19: 5 | B19: 材料费 | C19: 知情同意书、SOP、培训手册印刷 | D19: 固定 | E19: 1 | F19: 1 | G19: 2000 | H19: =IF(OR(F19="",G19=""),"",F19*G19) -> 2000 | I19: 按一版印刷估算；规划假设 | J19: =IF(D19="固定",H19,E19*G19) -> 2000
A20: 6 | B20: 劳务费 | C20: 社区协调员补贴（2 人×12 个月×600 元/月） | D20: 固定 | E20: 1 | F20: 24 | G20: 600 | H20: =IF(OR(F20="",G20=""),"",F20*G20) -> 14400 | I20: 24 人月；人力成本标准【待确认】；规划假设 | J20: =IF(D20="固定",H20,E20*G20) -> 14400
A21: 7 | B21: 劳务费 | C21: 随访访视劳务（每例 2 次：第 3、6 个月） | D21: 总例数 | E21: 2 | F21: =ROUND($C$5*E21,0) -> 672 | G21: 15 | H21: =IF(OR(F21="",G21=""),"",F21*G21) -> 10080 | I21: 访视次数与补贴标准为规划假设 | J21: =IF(D21="固定",H21,E21*G21) -> 30
A22: 8 | B22: 劳务费 | C22: 筛查劳务（按约 2:1 筛查—随机比） | D22: 总例数 | E22: 2 | F22: =ROUND($C$5*E22,0) -> 672 | G22: 5 | H22: =IF(OR(F22="",G22=""),"",F22*G22) -> 3360 | I22: 筛查—随机比参照 TASMINH4，实际转化率【待现场核实】 | J22: =IF(D22="固定",H22,E22*G22) -> 10
A23: 9 | B23: 数据管理与录入 | C23: 双录入/逻辑校验、数据管理 | D23: 固定 | E23: 1 | F23: 1 | G23: 6000 | H23: =IF(OR(F23="",G23=""),"",F23*G23) -> 6000 | I23: 按一批次估算；规划假设 | J23: =IF(D23="固定",H23,E23*G23) -> 6000
A24: 10 | B24: 差旅交通 | C24: 失访追踪上门随访与社区交通 | D24: 固定 | E24: 1 | F24: 1 | G24: 3000 | H24: =IF(OR(F24="",G24=""),"",F24*G24) -> 3000 | I24: 规划假设 | J24: =IF(D24="固定",H24,E24*G24) -> 3000
A25: 11 | B25: 伦理审查与随机化服务 | C25: 伦理审查费、随机化实施（信封/中心随机） | D25: 固定 | E25: 1 | F25: 1 | G25: 2000 | H25: =IF(OR(F25="",G25=""),"",F25*G25) -> 2000 | I25: 伦理委员会【待确认】；规划假设 | J25: =IF(D25="固定",H25,E25*G25) -> 2000
A26: 12 | B26: 专家咨询 | C26: 患教材料临床审核与第二统计师复核咨询费 | D26: 固定 | E26: 1 | F26: 1 | G26: 3000 | H26: =IF(OR(F26="",G26=""),"",F26*G26) -> 3000 | I26: 规划假设 | J26: =IF(D26="固定",H26,E26*G26) -> 3000
A27: 小计（1–12 项） | H27: =SUM(H15:H26) -> 89408
A28: 不可预见费（小计×费率） | H28: =ROUND(H27*$C$10,0) -> 4470
A29: 预算总计 | H29: =H27+H28 -> 93878
A30: 经费上限 | H30: =$C$11 -> 100000
A31: 余量（上限−总计） | H31: =H30-H29 -> 6122
A32: 总计占上限比例 | H32: =IF(H30=0,"",H29/H30) -> 0.93878

Sheet 规模联动测算
A1: 样本量敏感性矩阵 × 预算联动测算（δ×SD 组合对应总例数，含 15% 脱落膨胀）
A2: 状态声明：δ 与 SD 均为待确认参数，本表仅展示「不同规模下的预算量级」，不预设可行规模；设备单价引用输入假设【待询价】。规模变化时，联动类型为「干预例数」「总例数」的科目金额随例数变化，固定科目不变，另按不可预见费率 5% 计提。
A3: 组间差 δ（mmHg） | B3: 标准差 SD（mmHg） | C3: 总例数 | D3: 干预例数 | E3: 血压计台数 | F3: 干预联动金额（元） | G3: 总例数联动金额（元） | H3: 固定金额（元） | I3: 预算总计（元） | J3: 与上限比较
A4: 3 | B4: 12 | C4: 594 | D4: =C4/2 -> 297 | E4: =ROUND(D4*'预算与测算'!$E$15,0) -> 312 | F4: =E4*'预算与测算'!$G$15+ROUND((SUMIF('预算与测算'!$D$15:$D$26,"干预例数",'预算与测算'!$J$15:$J$26)-'预算与测算'!$J$15)*D4,0) -> 74580 | G4: =ROUND(SUMIF('预算与测算'!$D$15:$D$26,"总例数",'预算与测算'!$J$15:$J$26)*C4,0) -> 28512 | H4: =ROUND(SUMIF('预算与测算'!$D$15:$D$26,"固定",'预算与测算'!$J$15:$J$26),0) -> 31200 | I4: =ROUND((F4+G4+H4)*(1+'预算与测算'!$C$10),0) -> 141007 | J4: =IF(I4>'预算与测算'!$C$11,"超上限","上限内") -> 超上限
A5: 3 | B5: 15 | C5: 926 | D5: =C5/2 -> 463 | E5: =ROUND(D5*'预算与测算'!$E$15,0) -> 486 | F5: =E5*'预算与测算'!$G$15+ROUND((SUMIF('预算与测算'!$D$15:$D$26,"干预例数",'预算与测算'!$J$15:$J$26)-'预算与测算'!$J$15)*D5,0) -> 116180 | G5: =ROUND(SUMIF('预算与测算'!$D$15:$D$26,"总例数",'预算与测算'!$J$15:$J$26)*C5,0) -> 44448 | H5: =ROUND(SUMIF('预算与测算'!$D$15:$D$26,"固定",'预算与测算'!$J$15:$J$26),0) -> 31200 | I5: =ROUND((F5+G5+H5)*(1+'预算与测算'!$C$10),0) -> 201419 | J5: =IF(I5>'预算与测算'!$C$11,"超上限","上限内") -> 超上限
A6: 3 | B6: 18 | C6: 1332 | D6: =C6/2 -> 666 | E6: =ROUND(D6*'预算与测算'!$E$15,0) -> 699 | F6: =E6*'预算与测算'!$G$15+ROUND((SUMIF('预算与测算'!$D$15:$D$26,"干预例数",'预算与测算'!$J$15:$J$26)-'预算与测算'!$J$15)*D6,0) -> 167100 | G6: =ROUND(SUMIF('预算与测算'!$D$15:$D$26,"总例数",'预算与测算'!$J$15:$J$26)*C6,0) -> 63936 | H6: =ROUND(SUMIF('预算与测算'!$D$15:$D$26,"固定",'预算与测算'!$J$15:$J$26),0) -> 31200 | I6: =ROUND((F6+G6+H6)*(1+'预算与测算'!$C$10),0) -> 275348 | J6: =IF(I6>'预算与测算'!$C$11,"超上限","上限内") -> 超上限
A7: 4 | B7: 12 | C7: 336 | D7: =C7/2 -> 168 | E7: =ROUND(D7*'预算与测算'!$E$15,0) -> 176 | F7: =E7*'预算与测算'!$G$15+ROUND((SUMIF('预算与测算'!$D$15:$D$26,"干预例数",'预算与测算'!$J$15:$J$26)-'预算与测算'!$J$15)*D7,0) -> 42080 | G7: =ROUND(SUMIF('预算与测算'!$D$15:$D$26,"总例数",'预算与测算'!$J$15:$J$26)*C7,0) -> 16128 | H7: =ROUND(SUMIF('预算与测算'!$D$15:$D$26,"固定",'预算与测算'!$J$15:$J$26),0) -> 31200 | I7: =ROUND((F7+G7+H7)*(1+'预算与测算'!$C$10),0) -> 93878 | J7: =IF(I7>'预算与测算'!$C$11,"超上限","上限内") -> 上限内
A8: 4 | B8: 15 | C8: 520 | D8: =C8/2 -> 260 | E8: =ROUND(D8*'预算与测算'!$E$15,0) -> 273 | F8: =E8*'预算与测算'!$G$15+ROUND((SUMIF('预算与测算'!$D$15:$D$26,"干预例数",'预算与测算'!$J$15:$J$26)-'预算与测算'!$J$15)*D8,0) -> 65260 | G8: =ROUND(SUMIF('预算与测算'!$D$15:$D$26,"总例数",'预算与测算'!$J$15:$J$26)*C8,0) -> 24960 | H8: =ROUND(SUMIF('预算与测算'!$D$15:$D$26,"固定",'预算与测算'!$J$15:$J$26),0) -> 31200 | I8: =ROUND((F8+G8+H8)*(1+'预算与测算'!$C$10),0) -> 127491 | J8: =IF(I8>'预算与测算'!$C$11,"超上限","上限内") -> 超上限
A9: 4 | B9: 18 | C9: 750 | D9: =C9/2 -> 375 | E9: =ROUND(D9*'预算与测算'!$E$15,0) -> 394 | F9: =E9*'预算与测算'!$G$15+ROUND((SUMIF('预算与测算'!$D$15:$D$26,"干预例数",'预算与测算'!$J$15:$J$26)-'预算与测算'!$J$15)*D9,0) -> 94180 | G9: =ROUND(SUMIF('预算与测算'!$D$15:$D$26,"总例数",'预算与测算'!$J$15:$J$26)*C9,0) -> 36000 | H9: =ROUND(SUMIF('预算与测算'!$D$15:$D$26,"固定",'预算与测算'!$J$15:$J$26),0) -> 31200 | I9: =ROUND((F9+G9+H9)*(1+'预算与测算'!$C$10),0) -> 169449 | J9: =IF(I9>'预算与测算'!$C$11,"超上限","上限内") -> 超上限
A10: 5 | B10: 12 | C10: 216 | D10: =C10/2 -> 108 | E10: =ROUND(D10*'预算与测算'!$E$15,0) -> 113 | F10: =E10*'预算与测算'!$G$15+ROUND((SUMIF('预算与测算'!$D$15:$D$26,"干预例数",'预算与测算'!$J$15:$J$26)-'预算与测算'!$J$15)*D10,0) -> 27020 | G10: =ROUND(SUMIF('预算与测算'!$D$15:$D$26,"总例数",'预算与测算'!$J$15:$J$26)*C10,0) -> 10368 | H10: =ROUND(SUMIF('预算与测算'!$D$15:$D$26,"固定",'预算与测算'!$J$15:$J$26),0) -> 31200 | I10: =ROUND((F10+G10+H10)*(1+'预算与测算'!$C$10),0) -> 72017 | J10: =IF(I10>'预算与测算'!$C$11,"超上限","上限内") -> 上限内
A11: 5 | B11: 15 | C11: 336 | D11: =C11/2 -> 168 | E11: =ROUND(D11*'预算与测算'!$E$15,0) -> 176 | F11: =E11*'预算与测算'!$G$15+ROUND((SUMIF('预算与测算'!$D$15:$D$26,"干预例数",'预算与测算'!$J$15:$J$26)-'预算与测算'!$J$15)*D11,0) -> 42080 | G11: =ROUND(SUMIF('预算与测算'!$D$15:$D$26,"总例数",'预算与测算'!$J$15:$J$26)*C11,0) -> 16128 | H11: =ROUND(SUMIF('预算与测算'!$D$15:$D$26,"固定",'预算与测算'!$J$15:$J$26),0) -> 31200 | I11: =ROUND((F11+G11+H11)*(1+'预算与测算'!$C$10),0) -> 93878 | J11: =IF(I11>'预算与测算'!$C$11,"超上限","上限内") -> 上限内
A12: 5 | B12: 18 | C12: 480 | D12: =C12/2 -> 240 | E12: =ROUND(D12*'预算与测算'!$E$15,0) -> 252 | F12: =E12*'预算与测算'!$G$15+ROUND((SUMIF('预算与测算'!$D$15:$D$26,"干预例数",'预算与测算'!$J$15:$J$26)-'预算与测算'!$J$15)*D12,0) -> 60240 | G12: =ROUND(SUMIF('预算与测算'!$D$15:$D$26,"总例数",'预算与测算'!$J$15:$J$26)*C12,0) -> 23040 | H12: =ROUND(SUMIF('预算与测算'!$D$15:$D$26,"固定",'预算与测算'!$J$15:$J$26),0) -> 31200 | I12: =ROUND((F12+G12+H12)*(1+'预算与测算'!$C$10),0) -> 120204 | J12: =IF(I12>'预算与测算'!$C$11,"超上限","上限内") -> 超上限
A14: 注：招募能力（每月入组需求 108–666 人/月，两社区合计）与预算联动须在设备询价、名册核实后联合论证；本表不预设规模结论。

Sheet 说明与假设
A1: 编制说明与规划假设清单
A3: 1 | B3: 本预算为申报规划文本，全部金额与单价均为规划假设，不得作为实际支出依据；设备报价、人力成本、招募能力核实后须整体重算。
A4: 2 | B4: 测算基准规模取样本量敏感性矩阵中的 δ=5/SD=15（或 δ=4/SD=12）组合，总例数 336（干预 168/对照 168）；该规模本身为待确认参数，未锁定。
A5: 3 | B5: 样本量与效应量参数（组间差 δ、标准差 SD、基线—结局相关 r、沾染率）全部为待确认状态，来源与核对层级见《样本量参数来源表.md》；文献数值仅作各自情境参考，不构成本项目假设的上下限。
A6: 4 | B6: 预算测算基准规模下总计约 9.4 万元，占 10 万元上限约 94%，余量紧张：若实际入组规模高于基准组合，设备费与随访劳务将同步上升并可能突破上限（见「规模联动测算」表）；规模与预算须联合论证。
A7: 5 | B7: 现有研究数据为程序生成的合成数据（300 名模拟受试者），不得用作效应量依据，也不得写为真实预实验结果；模拟数据文件与未来真实数据物理分离。
A8: 6 | B8: 待确认项：两社区机构信息与登记名册、既往招募/失访率、医生可投入时间；设备型号与报价；人力成本标准；达标阈值（按申报年度现行指南）；伦理委员会信息；随机化实施细节。
A9: 7 | B9: 主要分析为 6 个月诊室收缩压的完整病例线性回归（调整基线收缩压、年龄、社区）；统计规则见《统计分析计划》v1.2，本预算不含数据分析软件采购费（使用 R/Python 开源软件）。
